helloworld.py
helloworld_pkg_tut-0.0.1.dist-info/LICENSE.txt
helloworld_pkg_tut-0.0.1.dist-info/METADATA
helloworld_pkg_tut-0.0.1.dist-info/WHEEL
helloworld_pkg_tut-0.0.1.dist-info/top_level.txt
helloworld_pkg_tut-0.0.1.dist-info/RECORD
